[
  {
    "id": "3df9b70c-18f3-ee11-aaf0-000d3a2f613f",
    "sierraId": "5669639",
    "shortAuthor": "Puusalu, Jaanika",
    "shortTitle": "Digitaalselt võimestatud riik. Kolm teoreetilist kontseptsiooni tänapäevase riigi olemuse selgitamiseks",
    "publishYear": "2024",
    "dateAdded": 1712319434558
  },
  {
    "id": "f767419b-17f3-ee11-aaf0-000d3a2f613f",
    "sierraId": "5669326",
    "shortAuthor": "Saar, Jüri, autor",
    "shortTitle": "Impact of Russia's Alternative Future Developments on Estonian Security",
    "publishYear": "2024",
    "dateAdded": 1712319434558
  },
  {
    "id": "d16f9a7c-16f3-ee11-aaf0-000d3a2f613f",
    "sierraId": "5651994",
    "shortAuthor": "Belova-Dalton, Oksana, autor",
    "shortTitle": "Raport Karen Drambjani radikaliseerumisest",
    "publishYear": "2024",
    "dateAdded": 1712319434558
  },
  {
    "id": "2a1bac1e-17f3-ee11-aaf0-000d3a2f613f",
    "sierraId": "5652669",
    "shortAuthor": "Saar, Jüri, autor",
    "shortTitle": "Venemaa võimalike arengute mõjust Eesti julgeolekule",
    "publishYear": "2024",
    "dateAdded": 1712319434558
  },
  {
    "id": "4f288cb1-cdf0-ee11-aaf0-000d3a2f613f",
    "sierraId": "5649432",
    "shortAuthor": "Pärn, Tõnu, autor",
    "shortTitle": "Kosmosetehnoloogiate rakendamise võimalused siseministeeriumi haldusalas",
    "publishYear": "2023",
    "dateAdded": 1712319434558
  },
  {
    "id": "20252bb7-2eec-ee11-aaf0-000d3a2f613f",
    "sierraId": "5646401",
    "shortAuthor": "Tikan, Mari, autor",
    "shortTitle": "Tuleohutuse seadus. Kommenteeritud väljaanne",
    "publishYear": "2023",
    "dateAdded": 1712319434558
  },
  {
    "id": "ddb61da1-55eb-ee11-aaf0-000d3a2f613f",
    "sierraId": "5637907",
    "shortAuthor": "Pärn, Tõnu, autor",
    "shortTitle": "Välisriikide MÕS-i vastase võitluse võrdlus",
    "publishYear": "2023",
    "dateAdded": 1712319434558
  }
]