[
  {
    "id": "6f2c951a-87bb-ef11-88cd-000d3a39fc20",
    "sierraId": "5641474",
    "shortAuthor": "Gulbranssen, Trygve",
    "shortTitle": "Ja taamal laulavad metsad ; Tuuled puhuvad Vaimudemäelt ; Ei lähe kõrvalteed",
    "publishYear": "2023",
    "dateAdded": 1734459688838
  },
  {
    "id": "5f2c951a-87bb-ef11-88cd-000d3a39fc20",
    "sierraId": "5523228",
    "shortAuthor": "Edwards, Mark",
    "shortTitle": "Harakad : hirm elab naaberkorteris ...",
    "publishYear": "2022",
    "dateAdded": 1734459688838
  }
]